meme_checkr/__init__.py
meme_checkr/main.py
meme_checkr-1.0.1.dist-info/LICENSE
meme_checkr-1.0.1.dist-info/METADATA
meme_checkr-1.0.1.dist-info/WHEEL
meme_checkr-1.0.1.dist-info/entry_points.txt
meme_checkr-1.0.1.dist-info/top_level.txt
meme_checkr-1.0.1.dist-info/RECORD
